Metadata-Version: 1.0
Name: binom-gaus-dist
Version: 0.2
Summary: Gaussian and Binomial distributions
Home-page: UNKNOWN
Author: Boni Oloff Nugraha
Author-email: bonioloff@gmail.com
License: UNKNOWN
Platform: UNKNOWN
